lm_saes/__init__.py
lm_saes/abstract_sae.py
lm_saes/activation/__init__.py
lm_saes/activation/factory.py
lm_saes/activation/processors/__init__.py
lm_saes/activation/processors/activation.py
lm_saes/activation/processors/cached_activation.py
lm_saes/activation/processors/core.py
lm_saes/activation/processors/huggingface.py
lm_saes/activation/processors/token.py
lm_saes/activation/writer.py
lm_saes/activation_functions.py
lm_saes/analysis/__init__.py
lm_saes/analysis/autointerp/__init__.py
lm_saes/analysis/autointerp/autointerp_base.py
lm_saes/analysis/autointerp/evaluation_prompts.py
lm_saes/analysis/autointerp/explanation_prompts.py
lm_saes/analysis/autointerp/feature_interpreter.py
lm_saes/analysis/direct_logit_attributor.py
lm_saes/analysis/feature_analyzer.py
lm_saes/analysis/post_analysis/__init__.py
lm_saes/analysis/post_analysis/base.py
lm_saes/analysis/post_analysis/clt.py
lm_saes/analysis/post_analysis/crosscoder.py
lm_saes/analysis/post_analysis/generic.py
lm_saes/analysis/post_analysis/lorsa.py
lm_saes/analysis/samples.py
lm_saes/backend/__init__.py
lm_saes/backend/language_model.py
lm_saes/circuit/__init__.py
lm_saes/circuit/attribution.py
lm_saes/circuit/graph.py
lm_saes/circuit/replacement_model.py
lm_saes/circuit/utils/__init__.py
lm_saes/circuit/utils/attn_scores_attribution.py
lm_saes/circuit/utils/attribution_utils.py
lm_saes/circuit/utils/create_graph_files.py
lm_saes/circuit/utils/disk_offload.py
lm_saes/circuit/utils/graph_file_utils.py
lm_saes/circuit/utils/transcoder_set.py
lm_saes/cli/__init__.py
lm_saes/cli/common.py
lm_saes/cli/create.py
lm_saes/cli/remove.py
lm_saes/cli/run.py
lm_saes/cli/show.py
lm_saes/cli/utils.py
lm_saes/clt.py
lm_saes/config.py
lm_saes/crosscoder.py
lm_saes/database.py
lm_saes/evaluator.py
lm_saes/initializer.py
lm_saes/kernels/__init__.py
lm_saes/kernels/entrypoints.py
lm_saes/kernels/kernels.py
lm_saes/lorsa.py
lm_saes/metrics.py
lm_saes/molt.py
lm_saes/optim.py
lm_saes/resource_loaders.py
lm_saes-2.0.0b8.dist-info/WHEEL
lm_saes-2.0.0b8.dist-info/entry_points.txt
lm_saes-2.0.0b8.dist-info/METADATA
lm_saes-2.0.0b8.dist-info/RECORD
