Metadata-Version: 2.3
Name: lm-saes
Version: 2.0.0b8
Summary: For OpenMOSS Mechanistic Interpretability Team's Sparse Autoencoder (SAE) research. Open-sourced and constantly updated.
Author: Xuyang Ge, Zhengfu He, Wentao Shu, Fukang Zhu, Lingjie Chen, Junxuan Wang
Author-email: Xuyang Ge <xyge20@fudan.edu.cn>, Zhengfu He <zfhe19@fudan.edu.cn>, Wentao Shu <wtshu20@fudan.edu.cn>, Fukang Zhu <fkzhu21@m.fudan.edu.cn>, Lingjie Chen <ljchen21@m.fudan.edu.cn>, Junxuan Wang <junxuanwang21@m.fudan.edu.cn>
License: MIT
Requires-Dist: transformer-lens
Requires-Dist: datasets>=3.0.2
Requires-Dist: transformers>=4.57.1
Requires-Dist: einops>=0.8.0
Requires-Dist: fastapi>=0.115.4
Requires-Dist: matplotlib>=3.9.2
Requires-Dist: numpy<2.0.0
Requires-Dist: pandas>=2.2.3
Requires-Dist: pymongo>=4.10.1
Requires-Dist: uvicorn>=0.32.0
Requires-Dist: wandb>=0.18.5
Requires-Dist: msgpack>=1.1.0
Requires-Dist: plotly>=5.24.1
Requires-Dist: openai>=1.52.2
Requires-Dist: tiktoken>=0.8.0
Requires-Dist: python-dotenv>=1.0.1
Requires-Dist: jaxtyping>=0.2.34
Requires-Dist: safetensors>=0.4.5
Requires-Dist: pydantic>=2.10.6
Requires-Dist: typer>=0.15.0
Requires-Dist: rich>=13.0.0
Requires-Dist: pyyaml>=6.0.2
Requires-Dist: tomlkit>=0.13.2
Requires-Dist: torch==2.9.0
Requires-Dist: torchvision>=0.22.1
Requires-Dist: pydantic-settings>=2.7.1
Requires-Dist: typing-extensions>=4.13.2
Requires-Dist: more-itertools>=10.7.0
Requires-Dist: json-repair>=0.44.1
Requires-Dist: typeguard>=4.4.1
Requires-Dist: torch-npu==2.9.0rc1 ; extra == 'npu'
Requires-Dist: sae-lens>=6.22.3 ; extra == 'sae-lens'
Requires-Dist: triton ; extra == 'triton'
Requires-Python: ==3.11.*
Provides-Extra: npu
Provides-Extra: sae-lens
Provides-Extra: triton
